perfect_cmaps/__init__.py
perfect_cmaps/color_utils.py
perfect_cmaps/colormaps.py
perfect_cmaps/customize_cmap.py
perfect_cmaps/optimization.py
perfect_cmaps/storage.py
perfect_cmaps/data/cielab_gamut_max_L.npy
perfect_cmaps/data/cielab_gamut_max_L_RGB.npy
perfect_cmaps/lab_control_points/README.md
perfect_cmaps/lab_control_points/__init__.py
perfect_cmaps/lab_control_points/cividish.json
perfect_cmaps/lab_control_points/diverging_hot_cool.json
perfect_cmaps/lab_control_points/mcyk.json
perfect_cmaps/lab_control_points/plasmoid.json
perfect_cmaps/lab_control_points/rgb_test.json
perfect_cmaps/lab_control_points/rgb_test2.json
perfect_cmaps/lab_control_points/salmiak.json
perfect_cmaps/lab_control_points/spectrum.json
perfect_cmaps/lab_control_points/viridish.json
perfect_cmaps/lab_control_points/viridish_2.json
perfect_cmaps/lab_control_points/__pycache__/__init__.cpython-38.pyc
perfect_cmaps/test_images/README.md
perfect_cmaps/test_images/__init__.py
perfect_cmaps/test_images/colourmaptest.tif
perfect_cmaps/test_images/__pycache__/__init__.cpython-38.pyc
perfect_cmaps/test_images/sem/BSD-sandpaper.jpg
perfect_cmaps/test_images/sem/Lily-Pollen.png
perfect_cmaps/test_images/sem/PhenomPharos-Gallery_Pyrite.jpg
perfect_cmaps/test_images/sem/PhenomXLGallery_5.jpg
perfect_cmaps/test_images/sem/Steel-mesh.png
perfect_cmaps/test_images/sem/charcoal4_49721153188_o-scaled.jpg
perfect_cmaps/test_images/sem/graphite5_49722003087_o-scaled.jpg
perfect_cmaps/test_images/sem/melamine-foam_49722002717_o-scaled.jpg
perfect_cmaps-1.4.0.dist-info/LICENSE
perfect_cmaps-1.4.0.dist-info/METADATA
perfect_cmaps-1.4.0.dist-info/WHEEL
perfect_cmaps-1.4.0.dist-info/top_level.txt
perfect_cmaps-1.4.0.dist-info/RECORD
