Metadata-Version: 2.1
Name: perfect-cmaps
Version: 1.4.0
Summary: Create amazing perceptually uniform colormaps with ease!
Home-page: https://github.com/m-ulmestrand/perfect-cmaps
Author: Mattias Ulmestrand
Author-email: m.ulmestrand@gmail.com
License: UNKNOWN
Platform: UNKNOWN
Classifier: Programming Language :: Python :: 3
Classifier: License :: OSI Approved :: Apache Software License
Classifier: Operating System :: OS Independent
Requires-Python: >=3.6
Requires-Dist: numpy
Requires-Dist: numba
Requires-Dist: pandas
Requires-Dist: matplotlib
Requires-Dist: colour-science
Requires-Dist: scipy
Requires-Dist: opencv-python-headless
Requires-Dist: importlib-resources
Requires-Dist: appdirs
Requires-Dist: tqdm
